{
 "metadata": {
  "language_info": {
   "codemirror_mode": {
    "name": "ipython",
    "version": 3
   },
   "file_extension": ".py",
   "mimetype": "text/x-python",
   "name": "python",
   "nbconvert_exporter": "python",
   "pygments_lexer": "ipython3",
   "version": "3.9.6"
  },
  "orig_nbformat": 4,
  "kernelspec": {
   "name": "python3",
   "display_name": "Python 3.9.6 64-bit"
  },
  "interpreter": {
   "hash": "14042f846377ef6343a74494fa226c1fd265be1d92c606c454a39715ac2907ed"
  }
 },
 "nbformat": 4,
 "nbformat_minor": 2,
 "cells": [
  {
   "cell_type": "code",
   "execution_count": 5,
   "metadata": {},
   "outputs": [
    {
     "output_type": "stream",
     "name": "stdout",
     "text": [
      "  4           0 LOAD_GLOBAL              0 (math)\n              2 LOAD_METHOD              1 (floor)\n              4 LOAD_CONST               1 (6.9785)\n              6 CALL_METHOD              1\n              8 STORE_FAST               0 (wert)\n\n  5          10 LOAD_CONST               2 ('hello wordly !!!')\n             12 STORE_FAST               1 (msg)\n\n  6          14 LOAD_GLOBAL              2 (print)\n             16 LOAD_FAST                0 (wert)\n             18 CALL_FUNCTION            1\n             20 POP_TOP\n             22 LOAD_CONST               0 (None)\n             24 RETURN_VALUE\n"
     ]
    }
   ],
   "source": [
    "import math\n",
    "import dis\n",
    "def printvalue():\n",
    "    wert = math.floor(6.9785)\n",
    "    msg = \"hello wordly !!!\"\n",
    "    print(wert)\n",
    "dis.dis(printvalue)\n"
   ]
  },
  {
   "cell_type": "code",
   "execution_count": null,
   "metadata": {},
   "outputs": [],
   "source": []
  }
 ]
}